agentspace_registration_cli.py
agentspace_registration_cli-1.0.0.dist-info/METADATA
agentspace_registration_cli-1.0.0.dist-info/WHEEL
agentspace_registration_cli-1.0.0.dist-info/entry_points.txt
agentspace_registration_cli-1.0.0.dist-info/top_level.txt
agentspace_registration_cli-1.0.0.dist-info/RECORD
