Metadata-Version: 2.4
Name: agentspace-registration-cli
Version: 1.0.0
Summary: A CLI for managing agents in Google Cloud Gemini Enterprise (supports both Agent Engine and A2A protocol agents).
Author: Henry Cheng
Project-URL: Homepage, https://github.com/0nri/agentspace-registration-cli
Project-URL: Bug Tracker, https://github.com/0nri/agentspace-registration-cli/issues
Classifier: Programming Language :: Python :: 3
Classifier: License :: OSI Approved :: MIT License
Classifier: Operating System :: OS Independent
Requires-Python: >=3.9
Requires-Dist: httpx
Requires-Dist: absl-py
